{
  "accounts": {
    "name": "Hisob",
    "items": {
      "username": {
        "name": "Foydalanuvchi nomi",
        "hint": "(@operator va boshqalar)",
        "text": "5 dan 32 gacha harf"
      },
      "bio": {
        "name": "Tarjimai hol",
        "hint": "",
        "text": "70 tagacha belgi"
      },
      "name_length": {
        "name": "Ism uzinligi",
        "hint": "",
        "text": "1 dan 64 gacha belgi"
      },
      "last_name_length": {
        "name": "Familiya uzunligi",
        "hint": "",
        "text": "0 dan 64 gacha belgi"
      },
      "self_destruction": {
        "name": "O'zini yo'q qilish davri",
        "hint": "Faol bo'lmaganida",
        "text": "1, 3, 6 va 12 oy (sukut bo'yicha 6)"
      },
      "spam_ban": {
        "name": "Spam taqiq",
        "hint": "",
        "text": "3 kun yoki undan ko'proq"
      },
      "channels_and_chats_number": {
        "name": "Kanallar va super guruhlar soni",
        "hint": "siz a'zo bo'lishingiz mumkin",
        "text": "500 tagacha (shu jumladan o'zingizniki)"
      },
      "gifs_number": {
        "name": "Saqlangan Giflar soni",
        "hint": "",
        "text": "200 gacha"
      },
      "video_length": {
        "name": "Video-avatar davomiyligi",
        "hint": "",
        "text": "10 daqiqagacha"
      },
      "groups_and_channels_creation": {
        "name": "Guruh va kanal yaratish",
        "hint": "",
        "text": "Kuniga 50 tagacha"
      },
      "accounts_number": {
        "name": "Hisoblar soni",
        "hint": "(rasmiy mijozlar)",
        "text": "3 tagacha"
      }
    }
  },
  "chats": {
    "name": "Suhbatlar va guruhlar",
    "items": {
      "participants_number": {
        "name": "Ishtirokchilar",
        "hint": "chegara ko'tarilishi mumkin",
        "text": "200,000 tagacha"
      },
      "admins_number": {
        "name": "Adminlar soni",
        "hint": "Guruhlarda",
        "text": "50 tagacha"
      },
      "bots_amount": {
        "name": "Bot yaratishlar soni",
        "hint": "Guruhlarda",
        "text": "20 tagacha"
      },
      "pinned_number": {
        "name": "Qadalgan xabarlardagi asosiy ro'yxat",
        "hint": "",
        "text": "5 tagacha  yoki + 5 ta maxfiy chat"
      },
      "group_name": {
        "name": "Guruh nomi va tavsifi",
        "hint": "",
        "text": "255 tagacha belgi"
      },
      "editing": {
        "name": "Xabar tahrirlash",
        "hint": "",
        "text": "yuborilganidan keyin 48 soat ichida; Saqlangan va cheklash huquqiga ega bo'lgan administratorlar uchun cheksiz"
      },
      "media_self_destruction": {
        "name": "Fotosurat va video o'z-o'zini yo'q qilish",
        "hint": "",
        "text": "1dan 60 sekundgacha"
      },
      "recent_actions": {
        "name": "So'nggi amallar",
        "hint": "(obunalar, xabarlar, va boshqalar)",
        "text": "oxirgi ikki kun"
      },
      "mentions_amount": {
        "name": "Eslatmalar soni",
        "hint": "Bir xabarda",
        "text": "up to 50, else notifications won't be sent"
      },
      "visible_messages": {
        "name": "Visible messages number",
        "hint": "in group",
        "text": "1,000,000 last messages"
      },
      "pinned_messages_number": {
        "name": "Pinned messages number",
        "hint": "",
        "text": "unlimited"
      },
      "participants_to_see_stats": {
        "name": "Number of participants to see statistics",
        "hint": "",
        "text": "at least 500"
      },
      "voice_chat_participants": {
        "name": "Voice Chat participants",
        "hint": "",
        "text": "up to 5,000"
      },
      "username_reservation": {
        "name": "Username change reservation",
        "hint": "(time before username will be available for everyone, not just the original owner)",
        "text": "about 15-30 minutes"
      },
      "participants_for_group_stickers": {
        "name": "Group-promoted stickers",
        "hint": "",
        "text": "groups with 100+ participants"
      }
    }
  },
  "channels": {
    "name": "Channels",
    "items": {
      "public_usernames": {
        "name": "Public usernames number",
        "hint": "for a single account",
        "text": "up to 10 (including groups)"
      },
      "username_length": {
        "name": "Length of @username",
        "hint": "",
        "text": "5 to 32 characters"
      },
      "channel_name": {
        "name": "Channel name and description",
        "hint": "",
        "text": "up to 255 characters"
      },
      "channel_admins": {
        "name": "Channel admins number",
        "hint": "(including bots; you can add a bot to your channel only by making it an admin)",
        "text": "up to 50 accounts"
      },
      "editing": {
        "name": "Posts editing",
        "hint": "",
        "text": "unlimited"
      },
      "subscribers": {
        "name": "Channel subscribers number",
        "hint": "",
        "text": "unlimited"
      },
      "visible_participants": {
        "name": "Visible subscribers",
        "hint": "for channel admin",
        "text": "200 people"
      },
      "channel_deletion": {
        "name": "Channel deletion",
        "hint": "",
        "text": "channels with more than 1K subscribers can be deleted only with Telegram support"
      },
      "private_channel_access": {
        "name": "Private channel access",
        "hint": "without subscription",
        "text": "up to 5 minutes once a day"
      },
      "invintations": {
        "name": "Inviting users",
        "hint": "",
        "text": "up to 200 people"
      },
      "followers_to_see_stats": {
        "name": "Number of subscribers to see statistics",
        "hint": "",
        "text": "at least 50"
      },
      "username_reservation": {
        "name": "Username change reservation",
        "hint": "(time before username will be available for everyone, not just the original owner)",
        "text": "about 15-30 minutes"
      }
    }
  },
  "messages": {
    "name": "Messages",
    "items": {
      "single_message_length": {
        "name": "One message length",
        "hint": "",
        "text": "up to 4,096 characters"
      },
      "media_descriptions": {
        "name": "Media captions",
        "hint": "",
        "text": "up to 1,024 characters"
      },
      "upload_size": {
        "name": "Fayl hajmi chegarasi",
        "hint": "",
        "text": "2.0 GB gacha"
      },
      "video_message_duration": {
        "name": "Video xabarning davomiyligi",
        "hint": "",
        "text": "1 daqiqagacha"
      },
      "album_size": {
        "name": "Rasmlar va videolar bitta pleylistda",
        "hint": "(albom)",
        "text": "10 tagacha "
      },
      "delayed_messages": {
        "name": "Rejalashtirilgan xabarlarning davomiyligi",
        "hint": "",
        "text": "100 tagacha"
      },
      "delaying_messages": {
        "name": "Jadval oralig'i",
        "hint": "",
        "text": "365 kungacha"
      }
    }
  },
  "folders": {
    "name": "Jildlar",
    "items": {
      "folder_amount": {
        "name": "Jildlar miqdori",
        "hint": "",
        "text": "10 tagacha"
      },
      "pinned_chats_in_folder": {
        "name": "Jilddagi qadalgan xabarlar ",
        "hint": "",
        "text": "100 tagacha"
      }
    }
  },
  "people_nearby": {
    "name": "Yaqin atrofdagi odamlar",
    "items": {
      "range": {
        "name": "Ko'rish oralig'i",
        "hint": "",
        "text": "Tahminan 12 kilometr"
      },
      "amount_of_people": {
        "name": "Visible users amount",
        "hint": "",
        "text": "up to 100 people"
      },
      "geochats_number": {
        "name": "Visible geochats number",
        "hint": "",
        "text": "up to 10 closest"
      }
    }
  },
  "bots": {
    "name": "Bots",
    "items": {
      "bots_amount": {
        "name": "Bots number",
        "hint": "(created by @BotFather)",
        "text": "up to 20 items"
      },
      "username length": {
        "name": "Length of @username",
        "hint": "for bots",
        "text": "5 to 32 characters"
      },
      "info_length": {
        "name": "Bot info length",
        "hint": "(/setabouttext)",
        "text": "up to 120 characters"
      },
      "description_length": {
        "name": "Bot description length",
        "hint": "",
        "text": "up to 512 characters"
      },
      "upload_limit_botapi": {
        "name": "File upload limit",
        "hint": "(BotAPI)",
        "text": "up to 50 MB"
      },
      "download_limit_botapi": {
        "name": "File download limit",
        "hint": "(BotAPI)",
        "text": "up to 20 MB"
      },
      "forwarding": {
        "name": "Message forwarding",
        "hint": "",
        "text": "up to 2,000 per hour"
      },
      "keys_in_keyboard_number": {
        "name": "Keyboard buttons number",
        "hint": "",
        "text": "up to 100 entities"
      },
      "formatting_data": {
        "name": "Message formatting data",
        "hint": "",
        "text": "up to 10 KB"
      },
      "formatting_entities": {
        "name": "Formatting entities",
        "hint": "(bold, cursive etc.)",
        "text": "up to 100 items"
      },
      "messaging_frequency": {
        "name": "Messages frequency",
        "hint": "(can be raised by BotSupport)",
        "text": "up to 30 messages per second; 20 per minute for public chats and channels"
      },
      "api_requests_frequency": {
        "name": "API requests frequency",
        "hint": "(can be raised by BotSupport)",
        "text": "up to 30 requests per second"
      },
      "bot_commands_count": {
        "name": "Commands amount",
        "hint": "(in BotFather)",
        "text": "0 to 100 commands"
      },
      "bot_command_name_length": {
        "name": "Command length",
        "hint": "(in BotFather)",
        "text": "from 1 to 32 characters"
      },
      "bot_command_description_length": {
        "name": "Command description length",
        "hint": "(in BotFather)",
        "text": "from 2 to 256 characters"
      },
      "start_payload_size": {
        "name": "Bot /start payload length",
        "hint": "",
        "text": "up to 64 characters"
      },
      "bot_alert_length": {
        "name": "Bot alert message length",
        "hint": "",
        "text": "up to 200 characters"
      }
    }
  },
  "search": {
    "name": "Search",
    "items": {
      "global_search": {
        "name": "Global search results",
        "hint": "",
        "text": "up to 10 items; up to 3 for Android"
      },
      "global_search_min_query": {
        "name": "Minimal query length",
        "hint": "for global search",
        "text": "at least 4 characters"
      }
    }
  },
  "stickers": {
    "name": "Stickers",
    "items": {
      "added_packs": {
        "name": "Added packs number",
        "hint": "",
        "text": "up to 200 items"
      },
      "favorite_stickers": {
        "name": "Favorite stickers number",
        "hint": "",
        "text": "up to 5 items"
      },
      "pack_size": {
        "name": "Stickers in a pack number",
        "hint": "",
        "text": "up to 120 for static, up to 50 for animated"
      },
      "sticker_size": {
        "name": "Sticker size",
        "hint": "",
        "text": "one side equal to 512px, the other side 512px or less; strictly 512x512 for animated"
      },
      "animation_duration": {
        "name": "Animation duration",
        "hint": "",
        "text": "up to 3 seconds"
      },
      "file_size": {
        "name": "Sticker file size",
        "hint": "",
        "text": "up to 512 KB for static, up to 64 KB for animated"
      },
      "fps": {
        "name": "FPS",
        "hint": "",
        "text": "either 30 or 60"
      }
    }
  },
  "telegraph": {
    "name": "Telegraph",
    "items": {
      "accounts_number": {
        "name": "Accounts number",
        "hint": "in @telegraph bot",
        "text": "up to 5 items"
      },
      "text_size": {
        "name": "Article size",
        "hint": "",
        "text": "up to 64 KiB"
      }
    }
  },
  "miscellaneous": {
    "name": "Miscellaneous",
    "items": {
      "properties": {
        "name": "Video avatar properties",
        "hint": "",
        "text": "800x800px, up to 2 MB"
      }
    }
  }
}
