{
  "accounts": {
    "name": "Konta",
    "items": {
      "username": {
        "name": "Nazwa użytkownika",
        "hint": "(np. @tpolska)",
        "text": "5 do 32 znaków"
      },
      "bio": {
        "name": "Biografia",
        "hint": "",
        "text": "do 70 znaków"
      },
      "name_length": {
        "name": "Długość imienia",
        "hint": "",
        "text": "od 1 do 64 znaków"
      },
      "last_name_length": {
        "name": "Długość nazwiska",
        "hint": "",
        "text": "od 0 do 64 znaków"
      },
      "self_destruction": {
        "name": "Okres samozniszczenia konta",
        "hint": "w przypadku braku aktywności",
        "text": "1, 3, 6 i 12 miesięcy (domyślnie 6)"
      },
      "spam_ban": {
        "name": "Blokada za SPAM",
        "hint": "",
        "text": "from 1 day up to forever"
      },
      "channels_and_chats_number": {
        "name": "Liczba kanałów i supergrup",
        "hint": ", do których możesz należeć",
        "text": "do 500 (w tym stworzone przez ciebie)"
      },
      "geochats_number": {
        "name": "Liczba geoczatów,",
        "hint": "w których możesz być członkiem",
        "text": "do 5 (w tym te stworzone przez Ciebie)"
      },
      "gifs_number": {
        "name": "Liczba zapisanych GIF-ów",
        "hint": "",
        "text": "do 200"
      },
      "video_length": {
        "name": "Czas trwania awatara wideo",
        "hint": "",
        "text": "do 10 sekund"
      },
      "groups_and_channels_creation": {
        "name": "Tworzenie grup i kanałów",
        "hint": "",
        "text": "do 50 dziennie"
      },
      "accounts_number": {
        "name": "Ilość kont",
        "hint": "(oficjalni klienci)",
        "text": "do 3"
      }
    }
  },
  "chats": {
    "name": "Czaty i grupy",
    "items": {
      "participants_number": {
        "name": "Liczba członków",
        "hint": "(limit stale rośnie)",
        "text": "do 200 000, ale nielimitowana w grupach rozgłoszeniowych"
      },
      "admins_number": {
        "name": "Liczba administratorów",
        "hint": "w grupie",
        "text": "do 50"
      },
      "bots_amount": {
        "name": "Liczba botów",
        "hint": "w grupie",
        "text": "do 20"
      },
      "pinned_number": {
        "name": "Przypięte czaty na głównej liście",
        "hint": "",
        "text": "do 5 czatów lub kanałów + 5 szyfrowanych czatów"
      },
      "group_name": {
        "name": "Nazwa i opis grupy",
        "hint": "",
        "text": "do 255 znaków"
      },
      "editing": {
        "name": "Edycja wiadomości",
        "hint": "",
        "text": "w ciągu 48 godzin od wysłania; nieograniczona w Zapisane wiadomości i dla administratorów z prawami przypinania"
      },
      "media_self_destruction": {
        "name": "Samozniszczenie zdjęć i filmów",
        "hint": "",
        "text": "1 do 60 sekund"
      },
      "recent_actions": {
        "name": "Ostatnie zdarzenia",
        "hint": "(subskrypcje, posty itp.)",
        "text": "ostatnie 2 dni"
      },
      "mentions_amount": {
        "name": "Liczba wzmianek",
        "hint": "w jednej wiadomości",
        "text": "do 50, w przeciwnym razie nie będzie powiadomienia"
      },
      "visible_messages": {
        "name": "Liczba widocznych wiadomości",
        "hint": "w grupie",
        "text": "1 000 000 ostatnich wiadomości"
      },
      "pinned_messages_number": {
        "name": "Liczba przypiętych wiadomości",
        "hint": "",
        "text": "bez limitu"
      },
      "participants_to_see_stats": {
        "name": "Liczba subskrybentów, aby zobaczyć statystyki",
        "hint": "",
        "text": "co najmniej 500"
      },
      "username_reservation": {
        "name": "Rezerwacja @nazwy użytkownika po zmianie",
        "hint": "(czas, w którym nazwa użytkownika jest dostępna tylko dla poprzedniego właściciela)",
        "text": "około 15-30 minut"
      },
      "participants_for_group_stickers": {
        "name": "Naklejki promujące grupę",
        "hint": "",
        "text": "grupy z ponad 100 uczestnikami"
      },
      "chat_role_length": {
        "name": "Długość tytułu administratora",
        "hint": "",
        "text": "do 16 znaków"
      },
      "chat_title_length": {
        "name": "Długość tytułu czatu",
        "hint": "",
        "text": "do 128 znaków"
      },
      "broadcast_group_access": {
        "name": "Konwertowanie supergrupy do grupy rozgłoszeniowej",
        "hint": "",
        "text": "dla czatów z ponad 199 000 członków"
      },
      "read_receipts_availability": {
        "name": "Widoczność potwierdzenia odczytu",
        "hint": "",
        "text": "dla czatów z maksymalnie 100 członkami; lista użytkowników jest dostępna tylko dla użytkownika, który wysłał wiadomość"
      },
      "read_receipts_lifetime": {
        "name": "Czas widoczności potwierdzenia odczytu",
        "hint": "",
        "text": "do 7 dni od wysłania wiadomości"
      }
    }
  },
  "voice_chats": {
    "name": "Czaty głosowe i wideo",
    "items": {
      "voice_chat_participants": {
        "name": "Słuchacze czatu audio",
        "hint": "",
        "text": "nielimitowani"
      },
      "video_chat_broadcast": {
        "name": "Transmisja wideo",
        "hint": "(kamera, udostępnianie ekranu)",
        "text": "do 30 użytkowników nadających jednocześnie"
      },
      "video_chat_viewers": {
        "name": "Widzowie transmisji wideo",
        "hint": "",
        "text": "oficjalnie ilość jest nieograniczona, ale w praktyce transmisja staje się niestabilna przy około 2000 jednoczesnych widzów"
      },
      "voice_chat_schedule": {
        "name": "Zaplanowane czaty",
        "hint": "",
        "text": "do 7 dni naprzód"
      }
    }
  },
  "channels": {
    "name": "Kanały",
    "items": {
      "public_usernames": {
        "name": "Liczba publicznych nazw użytkownika",
        "hint": "na pojedyncze konto",
        "text": "do 10 (w tym grupy)"
      },
      "username_length": {
        "name": "Długość @nazwy użytkownika",
        "hint": "",
        "text": "5 do 32 znaków"
      },
      "channel_name": {
        "name": "Długość nazwy kanału i opisu",
        "hint": "",
        "text": "do 255 znaków"
      },
      "channel_admins": {
        "name": "Ilość administratorów kanału",
        "hint": "(w tym boty; możesz dodać bota do swojego kanału tylko przez uczynienie go administratorem)",
        "text": "do 50 kont"
      },
      "editing": {
        "name": "Edycja postów",
        "hint": "",
        "text": "bez limitu (jeśli kanał ma podłączoną grupę dyskusyjną, posty starsze niż 2 tygodnie nie zostaną zaktualizowane na czacie)"
      },
      "subscribers": {
        "name": "Liczba subskrybentów kanałów",
        "hint": "",
        "text": "bez limitu"
      },
      "visible_participants": {
        "name": "Widoczni subskrybenci",
        "hint": "dla administratorów kanału",
        "text": "200 osób"
      },
      "channel_deletion": {
        "name": "Usuwanie kanału",
        "hint": "",
        "text": "kanał, który ma więcej niż 1 tys. subskrybentów, można usunąć tylko poprzez obsługę Telegrama"
      },
      "private_channel_access": {
        "name": "Przeglądanie prywatnych kanałów bez dołączania",
        "hint": "(dla kanałów z ponad 200 subskrybentami)",
        "text": "do 5 minut raz dziennie"
      },
      "invintations": {
        "name": "Zapraszanie użytkowników",
        "hint": "",
        "text": "do 200 osób"
      },
      "followers_to_see_stats": {
        "name": "Liczba subskrybentów, aby zobaczyć statystyki",
        "hint": "",
        "text": "co najmniej 50"
      },
      "username_reservation": {
        "name": "Rezerwacja @nazwy użytkownika po zmianie",
        "hint": "(czas, w którym nazwa użytkownika jest dostępna tylko dla poprzedniego właściciela)",
        "text": "około 15-30 minut"
      }
    }
  },
  "messages": {
    "name": "Wiadomości",
    "items": {
      "single_message_length": {
        "name": "Długość jednej wiadomości",
        "hint": "",
        "text": "do 4096 znaków"
      },
      "media_descriptions": {
        "name": "Opis plików multimedialnych",
        "hint": "",
        "text": "do 4096 znaków"
      },
      "upload_size": {
        "name": "Rozmiar wysłanych plików",
        "hint": "",
        "text": "up to 2.0 GB"
      },
      "file_name_length": {
        "name": "Długość nazwy pliku",
        "hint": "",
        "text": "do 60 znaków, pozostałe zostaną usunięte"
      },
      "video_message_duration": {
        "name": "Czas trwania wiadomości wideo",
        "hint": "",
        "text": "do 1 minuty"
      },
      "album_size": {
        "name": "Zdjęcia i filmy w pojedynczej wiadomości",
        "hint": "(album)",
        "text": "do 10 sztuk"
      },
      "delayed_messages": {
        "name": "Liczba zaplanowanych wiadomości",
        "hint": "",
        "text": "do 100 sztuk"
      },
      "delaying_messages": {
        "name": "Okres planowania wiadomości",
        "hint": "",
        "text": "do 365 dni"
      }
    }
  },
  "folders": {
    "name": "Foldery",
    "items": {
      "folder_amount": {
        "name": "Liczba folderów",
        "hint": "",
        "text": "do 10 folderów"
      },
      "pinned_chats_in_folder": {
        "name": "Przypięte czaty w folderze",
        "hint": "",
        "text": "do 100 czatów"
      }
    }
  },
  "people_nearby": {
    "name": "Ludzie w pobliżu",
    "items": {
      "range": {
        "name": "Promień widoczności",
        "hint": "",
        "text": "około 12 kilometrów"
      },
      "amount_of_people": {
        "name": "Liczba wyświetlonych użytkowników",
        "hint": "",
        "text": "do 100 osób"
      },
      "geochats_number": {
        "name": "Liczba wyświetlanych geoczatów",
        "hint": "",
        "text": "do 10 najbliższych"
      }
    }
  },
  "bots": {
    "name": "Boty",
    "items": {
      "bots_amount": {
        "name": "Liczba botów",
        "hint": "(utworzonych przez @BotFather)",
        "text": "do 20 sztuk"
      },
      "username length": {
        "name": "Długość @nazwy użytkownika",
        "hint": "dla bota",
        "text": "5 do 32 znaków"
      },
      "info_length": {
        "name": "Długość informacji o bocie",
        "hint": "(/setabouttext)",
        "text": "do 120 znaków"
      },
      "description_length": {
        "name": "Długość opisu bota",
        "hint": "",
        "text": "do 512 znaków"
      },
      "upload_limit_botapi": {
        "name": "Pliki wysłane przez bota",
        "hint": "bez lokalnego serwera API bota",
        "text": "do 50 MB"
      },
      "upload_limit_botapi_local": {
        "name": "Limit wysyłanego pliku",
        "hint": "z lokalnym serwerem Bot API",
        "text": "do 2000 MB"
      },
      "download_limit_botapi": {
        "name": "Pliki pobierane przez bota",
        "hint": "bez lokalnego serwera Bot API",
        "text": "do 20 MB"
      },
      "download_limit_botapi_local": {
        "name": "Limit pobieranego pliku",
        "hint": "bez lokalnego serwera Bot API",
        "text": "do 2000 MB"
      },
      "keys_in_keyboard_number": {
        "name": "Liczba przycisków",
        "hint": "",
        "text": "do 100 sztuk"
      },
      "formatting_data": {
        "name": "Dane formatowania wiadomości",
        "hint": "",
        "text": "do 10 KB"
      },
      "formatting_entities": {
        "name": "Formatowanie obiektów",
        "hint": "(pogrubienie, kursywa itp.)",
        "text": "do 100 elementów"
      },
      "messaging_frequency_broadcast": {
        "name": "Częstotliwość nadawania wiadomości",
        "hint": "dotyczy tylko aktywnego wysyłania powiadomień do innych nieaktywnych czatów",
        "text": "do 30 wiadomości na sekundę na czatach"
      },
      "messaging_frequency": {
        "name": "Częstotliwość wysyłania wiadomości",
        "hint": "na dowolnym czacie",
        "text": "do około jednej wiadomości na sekundę, może z wyjątkiem krótkich serii"
      },
      "messaging_frequency_groups": {
        "name": "Częstotliwość wysyłania wiadomości",
        "hint": "w czatach grupowych",
        "text": "do 20 wiadomości na sekundę na tym samym czacie"
      },
      "bot_commands_count": {
        "name": "Ilość poleceń",
        "hint": "(w BotFather)",
        "text": "0 do 100 poleceń"
      },
      "bot_command_name_length": {
        "name": "Długość polecenia",
        "hint": "(w BotFather)",
        "text": "od 1 do 32 znaków"
      },
      "bot_command_description_length": {
        "name": "Długość opisu polecenia",
        "hint": "",
        "text": "do 256 znaków, nie może być puste, gdy jest ustawione przez Bot API"
      },
      "start_payload_size": {
        "name": "Bot / początkowa długość metadanych",
        "hint": "stosowane w głębokim linkowaniu",
        "text": "do 64 bajtów"
      },
      "bot_alert_length": {
        "name": "Długość komunikatu ostrzegawczego bota",
        "hint": "",
        "text": "do 200 znaków"
      },
      "inline_max_items": {
        "name": "Ilość wyników inline",
        "hint": "",
        "text": "do 50 elementów na stronę"
      }
    }
  },
  "search": {
    "name": "Wyszukiwanie",
    "items": {
      "global_search": {
        "name": "Globalne wyniki wyszukiwania",
        "hint": "",
        "text": ""
      },
      "global_search_min_query": {
        "name": "Minimalna długość zapytania",
        "hint": "dla wyszukiwania globalnego",
        "text": "co najmniej 4 znaki"
      }
    }
  },
  "stickers": {
    "name": "Naklejki",
    "items": {
      "added_packs": {
        "name": "Liczba dodanych pakietów naklejek",
        "hint": "",
        "text": "do 200 sztuk"
      },
      "favorite_stickers": {
        "name": "Liczba ulubionych naklejek",
        "hint": "",
        "text": "do 5 elementów"
      },
      "pack_size": {
        "name": "Liczba naklejek w zestawie",
        "hint": "",
        "text": "do 120 w przypadku statycznych, do 50 w przypadku animowanych"
      },
      "sticker_size": {
        "name": "Rozmiar naklejki",
        "hint": "",
        "text": "jeden bok równy 512px, drugi bok 512px lub mniej; dokładnie 512x512px dla animowanej"
      },
      "animation_duration": {
        "name": "Czas trwania animacji",
        "hint": "",
        "text": "do 3 sekund"
      },
      "file_size": {
        "name": "Rozmiar pliku naklejki",
        "hint": "",
        "text": "do 512 KB w przypadku statycznej, do 64 KB w przypadku animowanej"
      },
      "fps": {
        "name": "FPS",
        "hint": "",
        "text": "30 lub 60"
      },
      "stickerpack_name_length": {
        "name": "Długość nazwy pakietu",
        "hint": "",
        "text": "do 64 znaków"
      },
      "stickerpack_url_length": {
        "name": "Długość adresu URL /addstickers dla pakietu naklejek",
        "hint": "",
        "text": "do 62 znaków"
      }
    }
  },
  "telegraph": {
    "name": "Telegraph",
    "items": {
      "accounts_number": {
        "name": "Liczba kont",
        "hint": "w bocie @telegraph",
        "text": "do 5 sztuk"
      },
      "text_size": {
        "name": "Rozmiar artykułu",
        "hint": "",
        "text": "do 64 KB"
      }
    }
  },
  "miscellaneous": {
    "name": "Różne",
    "items": {
      "properties": {
        "name": "Właściwości awatara wideo ",
        "hint": "",
        "text": "800x800px, do 2 MB"
      },
      "username_resolve_limit": {
        "name": "Limit rozwiązywania nazw użytkowników",
        "hint": "(zarówno dla botów, jak i kont użytkowników)",
        "text": "do 200 nazw użytkowników dziennie"
      }
    }
  }
}
