{
    "title": "Batasan Telegram — Telegram Info",
    "description": "Selalu perbarui batasan Telegram di 2020. Batasan pada panjang pesan, jumlah stiker dalam satu set, frekuensi pesan dalam Bot API, jumlah partisipan, perubahan, ukuran maksimal file dan sebagainya",
    "description_short": "Selalu perbarui batasan Telegram",
    "study": "| Pelajari",
    "big_title": "Batasan Telegram",
    "article_name": "Mengapa ada pembatasan",
    "article_p1": "Seperti halnya layanan lain, Telegram menggunakan pembatasan untuk memastikan pengguna mengikuti Kebijakan Penggunaan Wajar dan agar layanan tetap dapat berjalan.",
    "article_p2": "Tabel berikut berisikan daftar Batasan Telegram yang saat ini diketahui dan akan selalu diperbarui.",
    "loading": "Memuat...",
    "homepage": "Beranda",
    "language": "Bahasa",
    "search": "Cari",
    "native_language_name": "Bahasa Indonesia"
}